{
    "id": "exp1038983495",
    "personalInfo": {
        "title": null,
        "firstName": "Luisa",
        "lastName": "Lorenz",
        "fullName": "Luisa Lorenz",
        "image": "https://media.licdn.com/dms/image/v2/D4E03AQGywe1YxBtuBA/profile-displayphoto-shrink_100_100/profile-displayphoto-shrink_100_100/0/1666111445450?e=1745452800&v=beta&t=P0cVoK9bWPXDDCkaPq-q4mkOVQvB3REvSIrpgfPQ0cc",
        "email": null,
        "phone": null,
        "languages": [
            "Deutsch",
            "Englisch",
            "Französisch",
            "Katalanisch",
            "Spanisch"
        ],
        "allData": {
            "id": "1038983495",
            "profileId": "ACoAAD3toUcBcNJh6rFOm6YxO-BPlvx4yKoTaYA",
            "firstName": "Luisa",
            "lastName": "Lorenz",
            "occupation": "Global Business Management Graduate | Working Student in Economics @TUM Supporting Data-Driven & Innovative Research",
            "publicIdentifier": "luisalorenz",
            "trackingId": "FoTpGDc8Qj6G0YoUm0nlcQ==",
            "pictureUrl": "https://media.licdn.com/dms/image/v2/D4E03AQGywe1YxBtuBA/profile-displayphoto-shrink_100_100/profile-displayphoto-shrink_100_100/0/1666111445450?e=1745452800&v=beta&t=P0cVoK9bWPXDDCkaPq-q4mkOVQvB3REvSIrpgfPQ0cc",
            "coverImageUrl": "https://media.licdn.com/dms/image/v2/D4D16AQFt9RAvLJevXg/profile-displaybackgroundimage-shrink_200_800/profile-displaybackgroundimage-shrink_200_800/0/1737384902670?e=1745452800&v=beta&t=bBmYuR7lyZFnPwW5Xjf5sALfqufQa1-_v830XcnvMWc",
            "countryCode": "de",
            "geoUrn": "urn:li:fs_geo:103849782",
            "positions": [
                {
                    "title": "Assistant at TUM Chair of Economic",
                    "description": "In my role as a Working Student Assistant at the TUM Chair of Economics, I provide broad-based support across various tasks. \n\nMy key contributions include:\n• Economic Research: Conducting thorough economic literature research to lay a strong foundation for successful projects.\n• Project Support: Assisting with supplementary tasks to ensure an efficient workflow throughout all stages of the project. \n• Data Analytics: Creating impactful presentations, reports, and visuals while analyzing and interpreting data using statistical software.\n• Flexible and Reliable Support: Serving as a dependable team resource, readily adapting to changing tasks and challenges, and ensuring support at critical moments.\n\nIn my position, I have developed strong expertise in economic research and analysis. Most importantly, I have demonstrated my ability to thrive in both familiar and unfamiliar tasks while continuously consolidating and expanding my skill set. I deeply value the collaborative environment, mutual respect, and personal responsibility that I experience in my role, which fosters both professional support and personal confidence.",
                    "locationName": "Munich, Bavaria, Germany",
                    "timePeriod": {
                        "startDate": {
                            "month": 9,
                            "year": 2023
                        }
                    },
                    "company": {
                        "employeeCountRange": {
                            "start": 5001,
                            "end": 10000
                        },
                        "industries": [
                            "Research"
                        ],
                        "objectUrn": "urn:li:company:166283",
                        "entityUrn": "urn:li:fs_miniCompany:166283",
                        "name": "Technical University of Munich",
                        "showcase": false,
                        "active": true,
                        "logo": "https://media.licdn.com/dms/image/v2/D4D0BAQEPj4W4lIWpzQ/company-logo_200_200/company-logo_200_200/0/1719581261705/technische_universitat_munchen_logo?e=1747872000&v=beta&t=qhZOKI6W0rq_w2zi1Ny9LYLtP8N6HiU7q-kFebd6hUI",
                        "universalName": "technische-universitat-munchen",
                        "dashCompanyUrn": "urn:li:fsd_company:166283",
                        "trackingId": "7T1K9hoQT9ai4V0Q2Te8sA=="
                    },
                    "companyName": "Technical University of Munich"
                },
                {
                    "title": "Fitness Studio Operations Associate | Client Relation, Sales, & Training Support",
                    "description": "For 3+ years, I managed customer service and operational tasks at Level20 Fitness to support a well-functioning studio environment. Working 15 hours per week, I handled diverse responsibilities, including:\n• Customer Relations: Delivered high-quality service while providing tailored consulting on nutrition  and training, ensuring each client’s success in achieving personal goals.\n• Sales and Inventory: Handled in-studio sales and the effective management of inventory.\n• Customer Acquisition: Engaged with potential members and successfully secured new memberships. \n•Operational Support: Managed key financial and operational tasks, ensuring accuracy, and efficiency in daily studio operations.\n\nIn my role, I particularly developed strong skills in customer service and personalized client consulting. Most importantly, I built a strong ability to ensure seamless daily operations by effectively coordinating multiple tasks across finance, customer care, inventory management, and human resources",
                    "locationName": "Augsburg, Bavaria, Germany",
                    "timePeriod": {
                        "endDate": {
                            "month": 1,
                            "year": 2024
                        },
                        "startDate": {
                            "month": 10,
                            "year": 2020
                        }
                    },
                    "companyName": "Level20 Fitness"
                }
            ],
            "educations": [
                {
                    "degreeName": "Bachelor's degree",
                    "fieldOfStudy": "Global Business Management",
                    "schoolName": "University of Augsburg",
                    "timePeriod": {
                        "endDate": {
                            "month": 4,
                            "year": 2024
                        },
                        "startDate": {
                            "month": 10,
                            "year": 2019
                        }
                    }
                },
                {
                    "degreeName": "Exchange Semester ",
                    "fieldOfStudy": "Business Administration and Management, General",
                    "schoolName": "Universitat Internacional de Catalunya",
                    "timePeriod": {
                        "endDate": {
                            "month": 1,
                            "year": 2024
                        },
                        "startDate": {
                            "month": 9,
                            "year": 2023
                        }
                    }
                },
                {
                    "degreeName": "Auslandssemester",
                    "fieldOfStudy": "Wirtschaftswissenschaften und Sprachen",
                    "schoolName": "Universitat Internacional de Catalunya",
                    "timePeriod": {
                        "endDate": {
                            "month": 6,
                            "year": 2022
                        },
                        "startDate": {
                            "month": 1,
                            "year": 2022
                        }
                    }
                }
            ],
            "certifications": [
                {
                    "name": "Microsoft Office Specialist: Excel Associate (Office 2019)",
                    "timePeriod": {
                        "startDate": {
                            "month": 12,
                            "year": 2022
                        }
                    },
                    "authority": "Microsoft"
                },
                {
                    "name": "Microsoft Office Specialist: Word Associate (Office 2019)",
                    "timePeriod": {
                        "startDate": {
                            "month": 12,
                            "year": 2022
                        }
                    },
                    "authority": "Microsoft"
                },
                {
                    "name": "Microsoft Office Specialist: Associate (Office 2019)",
                    "timePeriod": {
                        "startDate": {
                            "month": 7,
                            "year": 2023
                        }
                    },
                    "authority": "Microsoft"
                },
                {
                    "name": "Microsoft Office Specialist: PowerPoint Associate (Office 2019)",
                    "timePeriod": {
                        "startDate": {
                            "month": 7,
                            "year": 2023
                        }
                    },
                    "authority": "Microsoft"
                },
                {
                    "name": "Cambridge English Certificate in Advanced English (CAE)",
                    "timePeriod": {
                        "startDate": {
                            "month": 12,
                            "year": 2024
                        }
                    },
                    "authority": "Cambridge University Press & Assessment"
                }
            ],
            "courses": [],
            "honors": [],
            "languages": [
                {
                    "name": "Deutsch",
                    "proficiency": "NATIVE_OR_BILINGUAL"
                },
                {
                    "name": "Englisch",
                    "proficiency": "FULL_PROFESSIONAL"
                },
                {
                    "name": "Französisch",
                    "proficiency": "ELEMENTARY"
                },
                {
                    "name": "Katalanisch",
                    "proficiency": "ELEMENTARY"
                },
                {
                    "name": "Spanisch",
                    "proficiency": "LIMITED_WORKING"
                }
            ],
            "skills": [
                "Project Support",
                "Statistical Software",
                "Data Analytics",
                "Economic Research"
            ],
            "volunteerExperiences": [],
            "headline": "Global Business Management Graduate | Working Student in Economics @TUM Supporting Data-Driven & Innovative Research",
            "summary": "Global Business Management Graduate @University of Augsburg with a strong affinity for strategic planning and intercultural communication | Working at the TUM Chair of Economics for 1+ year, supporting several of their innovative research projects\n\nSome examples of my accomplishments include:\n• Graduating in the top 5% of my Bachelor's degree, showcasing commitment to excellence \n• Completing two exchange semesters at the @UIC, enhancing my global perspective\n• Highly fluent in English and Spanish, with foundational knowledge in Catalan and French\n• Enthusiastic coffee lover with proficient skills after completing a barista course\n\nI am excited about opportunities to enhance my skills while working with like-minded and motivated individuals. I strive to connect with people from all over the world, believing in the importance of effective communication.",
            "student": false,
            "industryName": "Publishing",
            "industryUrn": "urn:li:fs_industry:82",
            "geoLocationName": "Augsburg, Bavaria",
            "geoCountryName": "Germany",
            "jobTitle": "Assistant at TUM Chair of Economic",
            "companyName": "Technical University of Munich",
            "companyPublicId": "technische-universitat-munchen",
            "companyLinkedinUrl": "https://www.linkedin.com/company/technische-universitat-munchen",
            "following": false,
            "followable": true,
            "followersCount": 106,
            "connectionsCount": 105,
            "connectionType": ""
        }
    },
    "institution": {
        "name": "Technical University of Munich",
        "position": "Assistant at TUM Chair of Economic",
        "department": null,
        "website": null
    },
    "expertise": {
        "primary": [],
        "secondary": [],
        "industries": [
            "Research"
        ]
    },
    "academicMetrics": {
        "publications": {
            "total": null,
            "sources": {
                "googleScholar": null,
                "scopus": null
            }
        }
    },
    "currentRole": {
        "title": "Assistant at TUM Chair of Economic",
        "organization": "Technical University of Munich",
        "focus": null
    },
    "profiles": {
        "linkedin": "https://www.linkedin.com/in/luisalorenz/",
        "company": "https://www.linkedin.com/company/technische-universitat-munchen"
    },
    "tags": [],
    "source": "LinkedIn",
    "experience": [
        {
            "title": "Assistant at TUM Chair of Economic",
            "description": "In my role as a Working Student Assistant at the TUM Chair of Economics, I provide broad-based support across various tasks. \n\nMy key contributions include:\n• Economic Research: Conducting thorough economic literature research to lay a strong foundation for successful projects.\n• Project Support: Assisting with supplementary tasks to ensure an efficient workflow throughout all stages of the project. \n• Data Analytics: Creating impactful presentations, reports, and visuals while analyzing and interpreting data using statistical software.\n• Flexible and Reliable Support: Serving as a dependable team resource, readily adapting to changing tasks and challenges, and ensuring support at critical moments.\n\nIn my position, I have developed strong expertise in economic research and analysis. Most importantly, I have demonstrated my ability to thrive in both familiar and unfamiliar tasks while continuously consolidating and expanding my skill set. I deeply value the collaborative environment, mutual respect, and personal responsibility that I experience in my role, which fosters both professional support and personal confidence.",
            "locationName": "Munich, Bavaria, Germany",
            "timePeriod": {
                "startDate": {
                    "month": 9,
                    "year": 2023
                }
            },
            "company": {
                "employeeCountRange": {
                    "start": 5001,
                    "end": 10000
                },
                "industries": [
                    "Research"
                ],
                "objectUrn": "urn:li:company:166283",
                "entityUrn": "urn:li:fs_miniCompany:166283",
                "name": "Technical University of Munich",
                "showcase": false,
                "active": true,
                "logo": "https://media.licdn.com/dms/image/v2/D4D0BAQEPj4W4lIWpzQ/company-logo_200_200/company-logo_200_200/0/1719581261705/technische_universitat_munchen_logo?e=1747872000&v=beta&t=qhZOKI6W0rq_w2zi1Ny9LYLtP8N6HiU7q-kFebd6hUI",
                "universalName": "technische-universitat-munchen",
                "dashCompanyUrn": "urn:li:fsd_company:166283",
                "trackingId": "7T1K9hoQT9ai4V0Q2Te8sA=="
            },
            "companyName": "Technical University of Munich"
        },
        {
            "title": "Fitness Studio Operations Associate | Client Relation, Sales, & Training Support",
            "description": "For 3+ years, I managed customer service and operational tasks at Level20 Fitness to support a well-functioning studio environment. Working 15 hours per week, I handled diverse responsibilities, including:\n• Customer Relations: Delivered high-quality service while providing tailored consulting on nutrition  and training, ensuring each client’s success in achieving personal goals.\n• Sales and Inventory: Handled in-studio sales and the effective management of inventory.\n• Customer Acquisition: Engaged with potential members and successfully secured new memberships. \n•Operational Support: Managed key financial and operational tasks, ensuring accuracy, and efficiency in daily studio operations.\n\nIn my role, I particularly developed strong skills in customer service and personalized client consulting. Most importantly, I built a strong ability to ensure seamless daily operations by effectively coordinating multiple tasks across finance, customer care, inventory management, and human resources",
            "locationName": "Augsburg, Bavaria, Germany",
            "timePeriod": {
                "endDate": {
                    "month": 1,
                    "year": 2024
                },
                "startDate": {
                    "month": 10,
                    "year": 2020
                }
            },
            "companyName": "Level20 Fitness"
        }
    ],
    "education": [
        {
            "degreeName": "Bachelor's degree",
            "fieldOfStudy": "Global Business Management",
            "schoolName": "University of Augsburg",
            "timePeriod": {
                "endDate": {
                    "month": 4,
                    "year": 2024
                },
                "startDate": {
                    "month": 10,
                    "year": 2019
                }
            }
        },
        {
            "degreeName": "Exchange Semester ",
            "fieldOfStudy": "Business Administration and Management, General",
            "schoolName": "Universitat Internacional de Catalunya",
            "timePeriod": {
                "endDate": {
                    "month": 1,
                    "year": 2024
                },
                "startDate": {
                    "month": 9,
                    "year": 2023
                }
            }
        },
        {
            "degreeName": "Auslandssemester",
            "fieldOfStudy": "Wirtschaftswissenschaften und Sprachen",
            "schoolName": "Universitat Internacional de Catalunya",
            "timePeriod": {
                "endDate": {
                    "month": 6,
                    "year": 2022
                },
                "startDate": {
                    "month": 1,
                    "year": 2022
                }
            }
        }
    ],
    "certifications": [
        {
            "name": "Microsoft Office Specialist: Excel Associate (Office 2019)",
            "timePeriod": {
                "startDate": {
                    "month": 12,
                    "year": 2022
                }
            },
            "authority": "Microsoft"
        },
        {
            "name": "Microsoft Office Specialist: Word Associate (Office 2019)",
            "timePeriod": {
                "startDate": {
                    "month": 12,
                    "year": 2022
                }
            },
            "authority": "Microsoft"
        },
        {
            "name": "Microsoft Office Specialist: Associate (Office 2019)",
            "timePeriod": {
                "startDate": {
                    "month": 7,
                    "year": 2023
                }
            },
            "authority": "Microsoft"
        },
        {
            "name": "Microsoft Office Specialist: PowerPoint Associate (Office 2019)",
            "timePeriod": {
                "startDate": {
                    "month": 7,
                    "year": 2023
                }
            },
            "authority": "Microsoft"
        },
        {
            "name": "Cambridge English Certificate in Advanced English (CAE)",
            "timePeriod": {
                "startDate": {
                    "month": 12,
                    "year": 2024
                }
            },
            "authority": "Cambridge University Press & Assessment"
        }
    ],
    "skills": [
        "Project Support",
        "Statistical Software",
        "Data Analytics",
        "Economic Research"
    ],
    "lastEnriched": "2025-02-17"
}