{
  "name": "Outfield",
  "description": "",
  "website": "",
  "location": "",
  "founded": "",
  "employees": "",
  "specialties": [
    {
      "permalink": "agriculture",
      "image_id": "db4bb759de5d44cca0ef7ad274d49191",
      "uuid": "6a733ac8-b79c-e2d2-55b9-cc3d66435eb6",
      "entity_def_id": "category",
      "value": "Agriculture"
    },
    {
      "permalink": "agtech",
      "image_id": "8c9a34f0959e40c3b75df7933f47fed2",
      "uuid": "fa736a2c-3108-8e06-9adf-fb7a75744f5b",
      "entity_def_id": "category",
      "value": "AgTech"
    },
    {
      "permalink": "artificial-intelligence",
      "image_id": "930c72a5a7b544999596ac1c0dc8b549",
      "uuid": "c4d8caf3-5fe7-359b-f9f2-2d708378e4ee",
      "entity_def_id": "category",
      "value": "Artificial Intelligence (AI)"
    },
    {
      "permalink": "horticulture",
      "image_id": "1cdb6db72aac44798cf1936aeb9f5c78",
      "uuid": "5ecb5545-454b-9dca-6eb3-1ea48692c3c4",
      "entity_def_id": "category",
      "value": "Horticulture"
    },
    {
      "permalink": "machine-learning",
      "image_id": "e83f580a280f48f39d789180bce8c2d9",
      "uuid": "5ea0cdb7-c9a6-47fc-50f8-c9b0fac04863",
      "entity_def_id": "category",
      "value": "Machine Learning"
    }
  ],
  "products": [],
  "partnerships": [],
  "technologies": [],
  "funding": {
    "total": "",
    "rounds": [],
    "last_funding_date": ""
  },
  "social_media": {
    "linkedin": "",
    "twitter": "",
    "facebook": ""
  },
  "type": "company",
  "category": "AI Company",
  "subcategory": "",
  "image_url": null,
  "data_sources": {
    "company_info": "human",
    "products": "human",
    "specialties": "human",
    "partnerships": "human",
    "market_presence": "human"
  },
  "data_quality": {
    "completeness": 0.9136908081345829,
    "verification_level": "high",
    "last_full_verification": "2024-02-05",
    "verification_method": "manual human verification",
    "missing_fields": []
  },
  "created_at": "2024-02-03T12:00:00.000Z",
  "last_updated": "2024-02-05T14:30:00.000Z",
  "verified": true,
  "verification_source": "human",
  "sources": {
    "company_info": {
      "name": {
        "url": "https://outfield.com/about",
        "verified": true,
        "last_checked": "2024-02-05"
      },
      "founding_date": {
        "url": "https://outfield.com/about",
        "verified": true,
        "last_checked": "2024-02-05"
      },
      "location": {
        "url": "https://outfield.com/contact",
        "verified": true,
        "last_checked": "2024-02-05"
      },
      "employees": {
        "url": "https://www.linkedin.com/company/outfield",
        "verified": true,
        "last_checked": "2024-02-05"
      }
    },
    "products_services": {},
    "specialties": {},
    "partnerships": {},
    "contact_info": {
      "email": {
        "url": "https://outfield.com/contact",
        "verified": true,
        "last_checked": "2024-02-05"
      },
      "phone": {
        "url": "https://outfield.com/contact",
        "verified": true,
        "last_checked": "2024-02-05"
      },
      "address": {
        "url": "https://outfield.com/contact",
        "verified": true,
        "last_checked": "2024-02-05"
      }
    },
    "social_media": {
      "linkedin": {
        "url": "",
        "verified": true,
        "last_checked": "2024-02-05"
      },
      "twitter": {
        "url": "",
        "verified": true,
        "last_checked": "2024-02-05"
      },
      "facebook": {
        "url": "",
        "verified": true,
        "last_checked": "2024-02-05"
      }
    },
    "image": null
  }
}