{
  "id": "exp188",
  "personalInfo": {
    "title": "Prof.",
    "firstName": "Markus",
    "lastName": "Lienkamp",
    "fullName": "Prof. Markus Lienkamp",
    "image": "/experts/prof--markus-lienkamp.jpg",
    "email": null,
    "phone": null,
    "languages": [
      "Deutsch",
      "Englisch"
    ]
  },
  "institution": {
    "name": "Technical University of Munich",
    "position": "Autonomous Driving",
    "department": null,
    "website": "Professor, Chair of Automotive Engineering"
  },
  "expertise": {
    "primary": [
      "Tel: +49 89 289 15353",
      "Email: sekretariat.ftm@ed.tum.de"
    ],
    "secondary": [],
    "industries": []
  },
  "academicMetrics": {
    "publications": {
      "total": null,
      "sources": {
        "googleScholar": null,
        "scopus": null
      }
    }
  },
  "currentRole": {
    "title": "Autonomous Driving",
    "organization": "Technical University of Munich",
    "focus": "Tel: +49 89 289 15353, Email: sekretariat.ftm@ed.tum.de"
  },
  "profiles": {
    "linkedin": null,
    "company": "Professor, Chair of Automotive Engineering"
  },
  "tags": [
    "Tel: +49 89 289 15353",
    "Email: sekretariat.ftm@ed.tum.de",
    "Autonomous Driving"
  ],
  "source": null,
  "expertise_sources": {},
  "data_sources": {
    "personal_info": "human",
    "publications": "human",
    "contact": "human",
    "academic_positions": "human",
    "awards": "human",
    "research_interests": "human"
  },
  "sources": {
    "personal_info": {
      "name": {
        "url": "https://undefined.com/people/exp188",
        "verified": true,
        "last_checked": "2024-02-05"
      },
      "dateOfBirth": {
        "url": "https://www.linkedin.com/in/exp188",
        "verified": true,
        "last_checked": "2024-02-05"
      },
      "nationality": {
        "url": "https://undefined.com/people/exp188",
        "verified": true,
        "last_checked": "2024-02-05"
      }
    },
    "expertise": {},
    "academic_background": {
      "fields": {},
      "universities": {},
      "degrees": {}
    },
    "projects": {},
    "publications": {},
    "contact_info": {
      "email": {
        "url": "https://undefined.com/contact",
        "verified": true,
        "last_checked": "2024-02-05"
      },
      "phone": {
        "url": "https://undefined.com/contact",
        "verified": true,
        "last_checked": "2024-02-05"
      },
      "address": {
        "url": "https://undefined.com/contact",
        "verified": true,
        "last_checked": "2024-02-05"
      },
      "office_hours": {
        "url": "https://undefined.com/contact",
        "verified": true,
        "last_checked": "2024-02-05"
      }
    }
  },
  "data_quality": {
    "completeness": 0.8661224606164238,
    "verification_level": "high",
    "last_full_verification": "2024-02-05",
    "verification_method": "manual human verification",
    "missing_fields": []
  },
  "created_at": "2024-02-03T12:00:00.000Z",
  "last_updated": "2024-02-05T14:30:00.000Z",
  "verified": true,
  "verification_source": "human",
  "image_url": null
}